README.md
setup.py
ppvt/__init__.py
ppvt/process.py
ppvt/run.py
ppvt/version_checker.py
ppvt.egg-info/PKG-INFO
ppvt.egg-info/SOURCES.txt
ppvt.egg-info/dependency_links.txt
ppvt.egg-info/entry_points.txt
ppvt.egg-info/requires.txt
ppvt.egg-info/top_level.txt